ams_messages/__init__.py
ams_messages/messages.py
ams_module/__init__.py
ams_module/serial.py
ams_dig_proc-0.0.9.dist-info/LICENSE
ams_dig_proc-0.0.9.dist-info/METADATA
ams_dig_proc-0.0.9.dist-info/WHEEL
ams_dig_proc-0.0.9.dist-info/top_level.txt
ams_dig_proc-0.0.9.dist-info/RECORD
