Metadata-Version: 2.1
Name: ams-dig-proc
Version: 0.0.9
Summary: Package for AMS-DIG-PROC board by VIGO PHOTONICS
Author-email: Paweł Sałek <psalek@vigo.com.pl>
License: MIT License
Project-URL: Homepage, https://ams-dig-proc.readthedocs.io/en/latest/index.html
Project-URL: Bug Tracker, https://gitlab.com/vigophotonics/ams-dig-proc
Classifier: Programming Language :: Python :: 3
Classifier: License :: OSI Approved :: MIT License
Classifier: Operating System :: OS Independent
Requires-Python: >=3.0
License-File: LICENSE
Requires-Dist: cobs
Requires-Dist: crccheck
Requires-Dist: pyserial
Requires-Dist: numpy
